range_tools.py
range_tools-0.1.0a3.dist-info/licenses/LICENSE
range_tools-0.1.0a3.dist-info/METADATA
range_tools-0.1.0a3.dist-info/WHEEL
range_tools-0.1.0a3.dist-info/top_level.txt
range_tools-0.1.0a3.dist-info/RECORD
