Metadata-Version: 2.4
Name: range-tools
Version: 0.1.0a3
Summary: Utility functions for working with Python ranges represented as (start, stop, step) tuples.
Author-email: Jifeng Wu <jifengwu2k@gmail.com>
License-Expression: MIT
Project-URL: Homepage, https://github.com/jifengwu2k/range-tools
Project-URL: Bug Tracker, https://github.com/jifengwu2k/range-tools/issues
Classifier: Programming Language :: Python :: 2
Classifier: Programming Language :: Python :: 3
Classifier: Operating System :: OS Independent
Requires-Python: >=2
License-File: LICENSE
Requires-Dist: typing; python_version < "3.5"
Dynamic: license-file
